<?xml version="1.0" encoding="utf-8" ?>
<dwsync>
<file name="ar-dz.js" server="webhosting2024.is.cc" local="131967183680000000" remote="132173281800000000" Dst="0" />
<file name="af.js" server="webhosting2024.is.cc" local="131967183680000000" remote="132173281800000000" Dst="0" />
<file name="ar-kw.js" server="webhosting2024.is.cc" local="131967183680000000" remote="132173281800000000" Dst="0" />
<file name="ar-ly.js" server="webhosting2024.is.cc" local="131967183680000000" remote="132173281800000000" Dst="0" />
<file name="ar-ma.js" server="webhosting2024.is.cc" local="131967183680000000" remote="132173281800000000" Dst="0" />
<file name="ar-sa.js" server="webhosting2024.is.cc" local="131967183680000000" remote="132173281800000000" Dst="0" />
<file name="ar.js" server="webhosting2024.is.cc" local="131967183680000000" remote="132173281800000000" Dst="0" />
<file name="az.js" server="webhosting2024.is.cc" local="131967183680000000" remote="132173281800000000" Dst="0" />
<file name="ar-tn.js" server="webhosting2024.is.cc" local="131967183680000000" remote="132173281800000000" Dst="0" />
<file name="bg.js" server="webhosting2024.is.cc" local="131967183680000000" remote="132173281800000000" Dst="0" />
<file name="bm.js" server="webhosting2024.is.cc" local="131967183680000000" remote="132173281800000000" Dst="0" />
<file name="be.js" server="webhosting2024.is.cc" local="131967183680000000" remote="132173281800000000" Dst="0" />
<file name="bo.js" server="webhosting2024.is.cc" local="131967183680000000" remote="132173281800000000" Dst="0" />
<file name="br.js" server="webhosting2024.is.cc" local="131967183680000000" remote="132173281800000000" Dst="0" />
<file name="bn.js" server="webhosting2024.is.cc" local="131967183680000000" remote="132173281800000000" Dst="0" />
<file name="ca.js" server="webhosting2024.is.cc" local="131967183680000000" remote="132173281800000000" Dst="0" />
<file name="cs.js" server="webhosting2024.is.cc" local="131967183680000000" remote="132173281800000000" Dst="0" />
<file name="bs.js" server="webhosting2024.is.cc" local="131967183680000000" remote="132173281800000000" Dst="0" />
<file name="cy.js" server="webhosting2024.is.cc" local="131967183680000000" remote="132173281800000000" Dst="0" />
<file name="da.js" server="webhosting2024.is.cc" local="131967183680000000" remote="132173281800000000" Dst="0" />
<file name="cv.js" server="webhosting2024.is.cc" local="131967183680000000" remote="132173281800000000" Dst="0" />
<file name="de-ch.js" server="webhosting2024.is.cc" local="131967183680000000" remote="132173281800000000" Dst="0" />
<file name="de.js" server="webhosting2024.is.cc" local="131967183680000000" remote="132173281800000000" Dst="0" />
<file name="de-at.js" server="webhosting2024.is.cc" local="131967183680000000" remote="132173281800000000" Dst="0" />
<file name="el.js" server="webhosting2024.is.cc" local="131967183680000000" remote="132173281800000000" Dst="0" />
<file name="en-au.js" server="webhosting2024.is.cc" local="131967183680000000" remote="132173281800000000" Dst="0" />
<file name="dv.js" server="webhosting2024.is.cc" local="131967183680000000" remote="132173281800000000" Dst="0" />
<file name="en-gb.js" server="webhosting2024.is.cc" local="131967183680000000" remote="132173281800000000" Dst="0" />
<file name="en-ie.js" server="webhosting2024.is.cc" local="131967183680000000" remote="132173281800000000" Dst="0" />
<file name="en-ca.js" server="webhosting2024.is.cc" local="131967183680000000" remote="132173281800000000" Dst="0" />
<file name="en-nz.js" server="webhosting2024.is.cc" local="131967183680000000" remote="132173281800000000" Dst="0" />
<file name="en-SG.js" server="webhosting2024.is.cc" local="131967183680000000" remote="132173281800000000" Dst="0" />
<file name="en-il.js" server="webhosting2024.is.cc" local="131967183680000000" remote="132173281800000000" Dst="0" />
<file name="es-us.js" server="webhosting2024.is.cc" local="131967183680000000" remote="132173281800000000" Dst="0" />
<file name="eo.js" server="webhosting2024.is.cc" local="131967183680000000" remote="132173281800000000" Dst="0" />
<file name="es-do.js" server="webhosting2024.is.cc" local="131967183680000000" remote="132173281800000000" Dst="0" />
<file name="et.js" server="webhosting2024.is.cc" local="131967183680000000" remote="132173281800000000" Dst="0" />
<file name="eu.js" server="webhosting2024.is.cc" local="131967183680000000" remote="132173281800000000" Dst="0" />
<file name="es.js" server="webhosting2024.is.cc" local="131967183680000000" remote="132173281800000000" Dst="0" />
<file name="fi.js" server="webhosting2024.is.cc" local="131967183680000000" remote="132173281800000000" Dst="0" />
<file name="fo.js" server="webhosting2024.is.cc" local="131967183680000000" remote="132173281800000000" Dst="0" />
<file name="fa.js" server="webhosting2024.is.cc" local="131967183680000000" remote="132173281800000000" Dst="0" />
<file name="fr.js" server="webhosting2024.is.cc" local="131967183680000000" remote="132173281800000000" Dst="0" />
<file name="fr-ca.js" server="webhosting2024.is.cc" local="131967183680000000" remote="132173281800000000" Dst="0" />
<file name="fr-ch.js" server="webhosting2024.is.cc" local="131967183680000000" remote="132173281800000000" Dst="0" />
<file name="ga.js" server="webhosting2024.is.cc" local="131967183680000000" remote="132173281800000000" Dst="0" />
<file name="gd.js" server="webhosting2024.is.cc" local="131967183680000000" remote="132173281800000000" Dst="0" />
<file name="fy.js" server="webhosting2024.is.cc" local="131967183680000000" remote="132173281800000000" Dst="0" />
<file name="gom-latn.js" server="webhosting2024.is.cc" local="131967183680000000" remote="132173281800000000" Dst="0" />
<file name="gu.js" server="webhosting2024.is.cc" local="131967183680000000" remote="132173281800000000" Dst="0" />
<file name="gl.js" server="webhosting2024.is.cc" local="131967183680000000" remote="132173281800000000" Dst="0" />
<file name="hi.js" server="webhosting2024.is.cc" local="131967183680000000" remote="132173281800000000" Dst="0" />
<file name="hr.js" server="webhosting2024.is.cc" local="131967183680000000" remote="132173281800000000" Dst="0" />
<file name="he.js" server="webhosting2024.is.cc" local="131967183680000000" remote="132173281800000000" Dst="0" />
<file name="hy-am.js" server="webhosting2024.is.cc" local="131967183680000000" remote="132173281800000000" Dst="0" />
<file name="id.js" server="webhosting2024.is.cc" local="131967183680000000" remote="132173281800000000" Dst="0" />
<file name="hu.js" server="webhosting2024.is.cc" local="131967183680000000" remote="132173281800000000" Dst="0" />
<file name="it.js" server="webhosting2024.is.cc" local="131967183680000000" remote="132173282400000000" Dst="0" />
<file name="is.js" server="webhosting2024.is.cc" local="131967183680000000" remote="132173281800000000" Dst="0" />
<file name="it-ch.js" server="webhosting2024.is.cc" local="131967183680000000" remote="132173281800000000" Dst="0" />
<file name="jv.js" server="webhosting2024.is.cc" local="131967183680000000" remote="132173281800000000" Dst="0" />
<file name="ja.js" server="webhosting2024.is.cc" local="131967183680000000" remote="132173281800000000" Dst="0" />
<file name="ka.js" server="webhosting2024.is.cc" local="131967183680000000" remote="132173282400000000" Dst="0" />
<file name="km.js" server="webhosting2024.is.cc" local="131967183680000000" remote="132173282400000000" Dst="0" />
<file name="kn.js" server="webhosting2024.is.cc" local="131967183680000000" remote="132173282400000000" Dst="0" />
<file name="kk.js" server="webhosting2024.is.cc" local="131967183680000000" remote="132173282400000000" Dst="0" />
<file name="ku.js" server="webhosting2024.is.cc" local="131967183680000000" remote="132173282400000000" Dst="0" />
<file name="ky.js" server="webhosting2024.is.cc" local="131967183680000000" remote="132173282400000000" Dst="0" />
<file name="ko.js" server="webhosting2024.is.cc" local="131967183680000000" remote="132173282400000000" Dst="0" />
<file name="lo.js" server="webhosting2024.is.cc" local="131967183680000000" remote="132173282400000000" Dst="0" />
<file name="lt.js" server="webhosting2024.is.cc" local="131967183680000000" remote="132173282400000000" Dst="0" />
<file name="lb.js" server="webhosting2024.is.cc" local="131967183680000000" remote="132173282400000000" Dst="0" />
<file name="mi.js" server="webhosting2024.is.cc" local="131967183680000000" remote="132173282400000000" Dst="0" />
<file name="lv.js" server="webhosting2024.is.cc" local="131967183680000000" remote="132173282400000000" Dst="0" />
<file name="me.js" server="webhosting2024.is.cc" local="131967183680000000" remote="132173282400000000" Dst="0" />
<file name="ml.js" server="webhosting2024.is.cc" local="131967183680000000" remote="132173282400000000" Dst="0" />
<file name="mn.js" server="webhosting2024.is.cc" local="131967183680000000" remote="132173282400000000" Dst="0" />
<file name="mk.js" server="webhosting2024.is.cc" local="131967183680000000" remote="132173282400000000" Dst="0" />
<file name="ms-my.js" server="webhosting2024.is.cc" local="131967183680000000" remote="132173282400000000" Dst="0" />
<file name="ms.js" server="webhosting2024.is.cc" local="131967183680000000" remote="132173282400000000" Dst="0" />
<file name="mr.js" server="webhosting2024.is.cc" local="131967183680000000" remote="132173282400000000" Dst="0" />
<file name="my.js" server="webhosting2024.is.cc" local="131967183680000000" remote="132173282400000000" Dst="0" />
<file name="nb.js" server="webhosting2024.is.cc" local="131967183680000000" remote="132173282400000000" Dst="0" />
<file name="mt.js" server="webhosting2024.is.cc" local="131967183680000000" remote="132173282400000000" Dst="0" />
<file name="ne.js" server="webhosting2024.is.cc" local="131967183680000000" remote="132173282400000000" Dst="0" />
<file name="nl-be.js" server="webhosting2024.is.cc" local="131967183680000000" remote="132173282400000000" Dst="0" />
<file name="nl.js" server="webhosting2024.is.cc" local="131967183680000000" remote="132173282400000000" Dst="0" />
<file name="pa-in.js" server="webhosting2024.is.cc" local="131967183680000000" remote="132173282400000000" Dst="0" />
<file name="pl.js" server="webhosting2024.is.cc" local="131967183680000000" remote="132173282400000000" Dst="0" />
<file name="nn.js" server="webhosting2024.is.cc" local="131967183680000000" remote="132173282400000000" Dst="0" />
<file name="pt.js" server="webhosting2024.is.cc" local="131967183680000000" remote="132173282400000000" Dst="0" />
<file name="ro.js" server="webhosting2024.is.cc" local="131967183680000000" remote="132173282400000000" Dst="0" />
<file name="pt-br.js" server="webhosting2024.is.cc" local="131967183680000000" remote="132173282400000000" Dst="0" />
<file name="sd.js" server="webhosting2024.is.cc" local="131967183680000000" remote="132173282400000000" Dst="0" />
<file name="se.js" server="webhosting2024.is.cc" local="131967183680000000" remote="132173282400000000" Dst="0" />
<file name="ru.js" server="webhosting2024.is.cc" local="131967183680000000" remote="132173282400000000" Dst="0" />
<file name="sk.js" server="webhosting2024.is.cc" local="131967183680000000" remote="132173282400000000" Dst="0" />
<file name="sl.js" server="webhosting2024.is.cc" local="131967183680000000" remote="132173282400000000" Dst="0" />
<file name="si.js" server="webhosting2024.is.cc" local="131967183680000000" remote="132173282400000000" Dst="0" />
<file name="sr.js" server="webhosting2024.is.cc" local="131967183680000000" remote="132173282400000000" Dst="0" />
<file name="sq.js" server="webhosting2024.is.cc" local="131967183680000000" remote="132173282400000000" Dst="0" />
<file name="sr-cyrl.js" server="webhosting2024.is.cc" local="131967183680000000" remote="132173282400000000" Dst="0" />
<file name="sv.js" server="webhosting2024.is.cc" local="131967183680000000" remote="132173282400000000" Dst="0" />
<file name="sw.js" server="webhosting2024.is.cc" local="131967183680000000" remote="132173282400000000" Dst="0" />
<file name="ss.js" server="webhosting2024.is.cc" local="131967183680000000" remote="132173282400000000" Dst="0" />
<file name="te.js" server="webhosting2024.is.cc" local="131967183680000000" remote="132173282400000000" Dst="0" />
<file name="tet.js" server="webhosting2024.is.cc" local="131967183680000000" remote="132173282400000000" Dst="0" />
<file name="ta.js" server="webhosting2024.is.cc" local="131967183680000000" remote="132173282400000000" Dst="0" />
<file name="th.js" server="webhosting2024.is.cc" local="131967183680000000" remote="132173282400000000" Dst="0" />
<file name="tl-ph.js" server="webhosting2024.is.cc" local="131967183680000000" remote="132173282400000000" Dst="0" />
<file name="tg.js" server="webhosting2024.is.cc" local="131967183680000000" remote="132173282400000000" Dst="0" />
<file name="tr.js" server="webhosting2024.is.cc" local="131967183680000000" remote="132173282400000000" Dst="0" />
<file name="tzl.js" server="webhosting2024.is.cc" local="131967183680000000" remote="132173282400000000" Dst="0" />
<file name="tlh.js" server="webhosting2024.is.cc" local="131967183680000000" remote="132173282400000000" Dst="0" />
<file name="tzm.js" server="webhosting2024.is.cc" local="131967183680000000" remote="132173282400000000" Dst="0" />
<file name="ug-cn.js" server="webhosting2024.is.cc" local="131967183680000000" remote="132173282400000000" Dst="0" />
<file name="tzm-latn.js" server="webhosting2024.is.cc" local="131967183680000000" remote="132173282400000000" Dst="0" />
<file name="ur.js" server="webhosting2024.is.cc" local="131967183680000000" remote="132173282400000000" Dst="0" />
<file name="uz-latn.js" server="webhosting2024.is.cc" local="131967183680000000" remote="132173282400000000" Dst="0" />
<file name="uk.js" server="webhosting2024.is.cc" local="131967183680000000" remote="132173282400000000" Dst="0" />
<file name="x-pseudo.js" server="webhosting2024.is.cc" local="131967183680000000" remote="132173282400000000" Dst="0" />
<file name="uz.js" server="webhosting2024.is.cc" local="131967183680000000" remote="132173282400000000" Dst="0" />
<file name="vi.js" server="webhosting2024.is.cc" local="131967183680000000" remote="132173282400000000" Dst="0" />
<file name="zh-cn.js" server="webhosting2024.is.cc" local="131967183680000000" remote="132173282400000000" Dst="0" />
<file name="zh-hk.js" server="webhosting2024.is.cc" local="131967183680000000" remote="132173282400000000" Dst="0" />
<file name="yo.js" server="webhosting2024.is.cc" local="131967183680000000" remote="132173282400000000" Dst="0" />
<file name="zh-tw.js" server="webhosting2024.is.cc" local="131967183680000000" remote="132173282400000000" Dst="0" />
<file name="af.js" server="ftp.thenerdyafrican.com//public_html/DTB/" local="131967183680000000" remote="132248155800000000" Dst="0" />
<file name="be.js" server="ftp.thenerdyafrican.com//public_html/DTB/" local="131967183680000000" remote="132248155800000000" Dst="0" />
<file name="cv.js" server="ftp.thenerdyafrican.com//public_html/DTB/" local="131967183680000000" remote="132248156400000000" Dst="0" />
<file name="en-SG.js" server="ftp.thenerdyafrican.com//public_html/DTB/" local="131967183680000000" remote="132248156400000000" Dst="0" />
<file name="it-ch.js" server="ftp.thenerdyafrican.com//public_html/DTB/" local="131967183680000000" remote="132248157000000000" Dst="0" />
<file name="ar-dz.js" server="ftp.thenerdyafrican.com//public_html/DTB/" local="131967183680000000" remote="132248817600000000" Dst="0" />
<file name="bg.js" server="ftp.thenerdyafrican.com//public_html/DTB/" local="131967183680000000" remote="132248817600000000" Dst="0" />
<file name="lt.js" server="ftp.thenerdyafrican.com//public_html/DTB/" local="131967183680000000" remote="132248817600000000" Dst="0" />
<file name="sl.js" server="ftp.thenerdyafrican.com//public_html/DTB/" local="131967183680000000" remote="132248818200000000" Dst="0" />
<file name="tzm.js" server="ftp.thenerdyafrican.com//public_html/DTB/" local="131967183680000000" remote="132248818200000000" Dst="0" />
<file name="ss.js" server="ftp.thenerdyafrican.com//public_html/DTB/" local="131967183680000000" remote="132248818200000000" Dst="0" />
<file name="uk.js" server="ftp.thenerdyafrican.com//public_html/DTB/" local="131967183680000000" remote="132248818200000000" Dst="0" />
<file name="yo.js" server="ftp.thenerdyafrican.com//public_html/DTB/" local="131967183680000000" remote="132248818200000000" Dst="0" />
</dwsync>